Metadata-Version: 2.1
Name: blackbox-mpc2
Version: 0.3.0.1
Summary: Fork of BlackBox MPC - Model Predictive Control withsampling based optimizers
Home-page: https://github.com/Malborne/blackbox_mpc2.git
Author: Ossama Ahmed, Jonas Rothfuss, Ibrahim Ahmed
Author-email: ibr_alameen@hotmail.com
License: UNKNOWN
Platform: UNKNOWN
